[
  {
    "timestamp": "2024-10-24T15:49:58.100100",
    "symbol": "BTCUSDT",
    "action": "SELL",
    "entry_price": 67003.4,
    "exit_price": 66986.0,
    "amount": 0.00037321231302063116,
    "profit_loss": 0.00649389424655681,
    "profit_loss_percentage": 0.025968831432426086,
    "reason": "Position Closed / Swapped to Buy!"
  },
  {
    "timestamp": "2024-10-24T15:52:32.692540",
    "symbol": "BTCUSDT",
    "action": "BUY",
    "entry_price": 67013.7,
    "exit_price": 66899.2,
    "amount": 0.00037364348731928735,
    "profit_loss": -0.0427821792980584,
    "profit_loss_percentage": -0.17086058522361847,
    "reason": "Position Closed"
  },
  {
    "timestamp": "2024-10-24T15:57:19.338000",
    "symbol": "BTCUSDT",
    "action": "BUY",
    "entry_price": 66867.4,
    "exit_price": 66852.1,
    "amount": 0.00037397157816005983,
    "profit_loss": -0.0057217651458445614,
    "profit_loss_percentage": -0.022881104992849073,
    "reason": "Position Closed / Swapped to Sell!"
  },
  {
    "timestamp": "2024-10-24T16:07:25.413565",
    "symbol": "BTCUSDT",
    "action": "SELL",
    "entry_price": 66867.4,
    "exit_price": 66830.6,
    "amount": 0.0003740622259994194,
    "profit_loss": 0.01376548991677428,
    "profit_loss_percentage": 0.05503429174753073,
    "reason": "Position Closed"
  },
  {
    "timestamp": "2024-10-24T16:27:31.676263",
    "symbol": "BTCUSDT",
    "action": "SELL",
    "entry_price": 66826.0,
    "exit_price": 66953.5,
    "amount": 0.00037338845542637977,
    "profit_loss": -0.04760702806686342,
    "profit_loss_percentage": -0.19079400233442073,
    "reason": "Position Closed"
  },
  {
    "timestamp": "2024-10-24T16:55:52.667894",
    "symbol": "BTCUSDT",
    "action": "SELL",
    "entry_price": 66891.7,
    "exit_price": 66840.0,
    "amount": 0.00037402752842609214,
    "profit_loss": 0.019337223219627876,
    "profit_loss_percentage": 0.07728911060714123,
    "reason": "Position Closed"
  },
  {
    "timestamp": "2024-10-24T17:10:47.042575",
    "symbol": "BTCUSDT",
    "action": "BUY",
    "entry_price": 66939.1,
    "exit_price": 66864.4,
    "amount": 0.00037383177570093456,
    "profit_loss": -0.027925233644864163,
    "profit_loss_percentage": -0.11159397123655926,
    "reason": "Position Closed"
  }
]