{"global_entry_price": 2610.93, "global_position_entry_time": "2024-10-23T07:17:30.770265+00:00", "global_position_side": "buy", "last_candle_time": "2024-10-23T07:28:00+00:00", "last_candle_cross": {"status": true, "type": "crossover", "candle": {"open": 2608.59, "high": 2609.38, "low": 2607.66, "close": 2608.75, "volume": 2010.781, "time": "23/10/2024 14:14", "rsi": 32.67}}, "last_focus_price": null, "last_focus_stopprice": 2607.66, "is_wait_candle": false, "is_in_position": true, "is_swapping": false, "isTry_last_entry": false, "entry_candle": {"timestamp": 1729667820000, "open": 2610.3, "high": 2614.09, "low": 2610.0, "close": 2613.24, "volume": 3581.433}, "entry_price": null, "entry_side": null, "entry_stoploss_price": null}